server/.python-version
server/README.md
server/auth.py
server/cli.py
server/database.py
server/main.py
server/schemas.py
server/tools/__init__.py
server/tools/academic_tools.py
server/tools/admin_tools.py
server/tools/admission_form_tools.py
server/tools/admission_tools.py
server/tools/audit_tools.py
server/tools/contact_tools.py
server/tools/event_tools.py
server/tools/faculty_tools.py
server/tools/fee_tools.py
server/tools/hostel_tools.py
server/tools/library_tools.py
server/tools/news_tools.py
server/tools/result_tools.py
server/tools/scholarship_tools.py
server/tools/timetable_tools.py
server/tools/transport_tools.py
server/tools/user_tools.py
uaar_university_mcp-0.1.0.dist-info/METADATA
uaar_university_mcp-0.1.0.dist-info/WHEEL
uaar_university_mcp-0.1.0.dist-info/licenses/LICENSE
uaar_university_mcp-0.1.0.dist-info/RECORD
