Metadata-Version: 2.4
Name: uaar-university-mcp
Version: 0.1.0
Summary: UAAR University MCP Server
Project-URL: Homepage, https://github.com/uaar-university/uaar-university-mcp
Project-URL: Repository, https://github.com/uaar-university/uaar-university-mcp.git
Project-URL: Documentation, https://github.com/uaar-university/uaar-university-mcp#readme
Project-URL: Issues, https://github.com/uaar-university/uaar-university-mcp/issues
Author: UAAR University
Maintainer: UAAR University
License: MIT License
License-File: LICENSE
Keywords: academic,ai-agent,claude,education,mcp,university
Classifier: Development Status :: 4 - Beta
Classifier: Intended Audience :: Developers
Classifier: Intended Audience :: Education
Classifier: License :: OSI Approved :: MIT License
Classifier: Operating System :: OS Independent
Classifier: Programming Language :: Python
Classifier: Programming Language :: Python :: 3
Classifier: Programming Language :: Python :: 3.10
Classifier: Programming Language :: Python :: 3.11
Classifier: Programming Language :: Python :: 3.12
Classifier: Programming Language :: Python :: 3.13
Classifier: Topic :: Education
Classifier: Topic :: Software Development
Classifier: Topic :: Software Development :: Libraries
Classifier: Topic :: Software Development :: Libraries :: Python Modules
Requires-Python: >=3.10
Requires-Dist: bcrypt
Requires-Dist: fastapi
Requires-Dist: mcp
Requires-Dist: python-jose[cryptography]
Requires-Dist: python-multipart
Requires-Dist: rich
Requires-Dist: uvicorn
